deskew/__init__.py
deskew/fast_deskew.py
fast_deskew_cv-1.0.0.dist-info/LICENSE
fast_deskew_cv-1.0.0.dist-info/METADATA
fast_deskew_cv-1.0.0.dist-info/WHEEL
fast_deskew_cv-1.0.0.dist-info/top_level.txt
fast_deskew_cv-1.0.0.dist-info/RECORD
