Metadata-Version: 2.1
Name: fast-deskew-cv
Version: 1.0.0
Summary: A fast deskew using hough line transform
Author-email: HO ZhenWai Olivier <hozhenwai@gmail.com>
License: MIT License 
Project-URL: Source, https://github.com/HOZHENWAI/fast_deskew.git
Project-URL: Tracker, https://github.com/HOZHENWAI/fast_deskew/issues
Keywords: deskew,fast
Requires-Python: >=3.10
License-File: LICENSE
Requires-Dist: numpy
Requires-Dist: opencv-python
Provides-Extra: dev
Requires-Dist: black >=24.1.1 ; extra == 'dev'
Requires-Dist: git-changelog >=2.4.0 ; extra == 'dev'
Requires-Dist: isort >=5.13.2 ; extra == 'dev'
Requires-Dist: pre-commit >=3.6.0 ; extra == 'dev'
Requires-Dist: pylint >=3.0.3 ; extra == 'dev'
Requires-Dist: pytest-assume >=2.4.3 ; extra == 'dev'
Requires-Dist: pytest-cov >=4.1.0 ; extra == 'dev'
Requires-Dist: pytest-mock >=3.12 ; extra == 'dev'
Requires-Dist: pytest >=8.0.0 ; extra == 'dev'
